mysqloop/BuildAttrs.py
mysqloop/Model.py
mysqloop/Users.py
mysqloop/__init__.py
mysqloop/mysqloop.py
mysql_oop-0.1.6.dist-info/LICENSE
mysql_oop-0.1.6.dist-info/METADATA
mysql_oop-0.1.6.dist-info/WHEEL
mysql_oop-0.1.6.dist-info/top_level.txt
mysql_oop-0.1.6.dist-info/RECORD
