Metadata-Version: 2.1
Name: mysql-oop
Version: 0.1.6
Summary: python mysql OOP class
Home-page: https://github.com/hahadu/mysql-py-oop
Author: hahadu
Author-email: mhyzhu@163.com
Project-URL: Bug Tracker, https://github.com/hahadu/mysql-py-oop/issues
Classifier: Programming Language :: Python :: 3
Classifier: License :: OSI Approved :: MIT License
Classifier: Operating System :: OS Independent
Requires-Python: >=3.6
License-File: LICENSE
